odoo/addons/shift_attendance/README.rst
odoo/addons/shift_attendance/__init__.py
odoo/addons/shift_attendance/__manifest__.py
odoo/addons/shift_attendance/data/cron.xml
odoo/addons/shift_attendance/data/mail_template.xml
odoo/addons/shift_attendance/data/system_parameter.xml
odoo/addons/shift_attendance/demo/users.xml
odoo/addons/shift_attendance/demo/workers.xml
odoo/addons/shift_attendance/i18n/fr_BE.po
odoo/addons/shift_attendance/i18n/nl_BE.po
odoo/addons/shift_attendance/i18n/shift_attendance.pot
odoo/addons/shift_attendance/models/__init__.py
odoo/addons/shift_attendance/models/attendance_sheet.py
odoo/addons/shift_attendance/models/res_config_settings.py
odoo/addons/shift_attendance/readme/CONTRIBUTORS.rst
odoo/addons/shift_attendance/readme/DESCRIPTION.rst
odoo/addons/shift_attendance/readme/HISTORY.rst
odoo/addons/shift_attendance/security/group.xml
odoo/addons/shift_attendance/security/ir.model.access.csv
odoo/addons/shift_attendance/static/description/index.html
odoo/addons/shift_attendance/tests/__init__.py
odoo/addons/shift_attendance/tests/test_shift.py
odoo/addons/shift_attendance/views/attendance_sheet.xml
odoo/addons/shift_attendance/views/res_config_settings_view.xml
odoo/addons/shift_attendance/wizard/__init__.py
odoo/addons/shift_attendance/wizard/generate_missing_attendance_sheets.py
odoo/addons/shift_attendance/wizard/generate_missing_attendance_sheets.xml
odoo/addons/shift_attendance/wizard/validate_attendance_sheet.py
odoo/addons/shift_attendance/wizard/validate_attendance_sheet.xml
odoo_addon_shift_attendance-16.0.1.0.0.11.dist-info/METADATA
odoo_addon_shift_attendance-16.0.1.0.0.11.dist-info/WHEEL
odoo_addon_shift_attendance-16.0.1.0.0.11.dist-info/top_level.txt
odoo_addon_shift_attendance-16.0.1.0.0.11.dist-info/RECORD
