Metadata-Version: 2.1
Name: odoo-addon-shift_attendance
Version: 16.0.1.0.0.11
Requires-Python: >=3.10
Requires-Dist: odoo-addon-eater>=16.0dev,<16.1dev
Requires-Dist: odoo-addon-member_card>=16.0dev,<16.1dev
Requires-Dist: odoo-addon-shift>=16.0dev,<16.1dev
Requires-Dist: odoo-addon-shift_worker_status>=16.0dev,<16.1dev
Requires-Dist: odoo>=16.0a,<16.1dev
Summary: Volunteer Timetable Management
Home-page: https://github.com/beescoop/Obeesdoo
License: AGPL-3
Author: Elouan Le Bars, Coop IT Easy SC, Odoo Community Association (OCA)
Author-email: support@odoo-community.org
Classifier: Programming Language :: Python
Classifier: Framework :: Odoo
Classifier: Framework :: Odoo :: 16.0
Classifier: License :: OSI Approved :: GNU Affero General Public License v3
